{
  "project_info": {
    "project_number": "322516920929",
    "firebase_url": "https://testeionic3push-144b6.firebaseio.com",
    "project_id": "testeionic3push-144b6",
    "storage_bucket": "testeionic3push-144b6.appspot.com"
  },
  "client": [
    {
      "client_info": {
        "mobilesdk_app_id": "1:322516920929:android:2c12d2ac30aa3c51d19820",
        "android_client_info": {
          "package_name": "com.uniara.fecapp"
        }
      },
      "oauth_client": [
        {
          "client_id": "322516920929-on448i6sc9cb6rn3bj4cfgab37kpg9vo.apps.googleusercontent.com",
          "client_type": 3
        }
      ],
      "api_key": [
        {
          "current_key": "AIzaSyDyZlP13QOu1zsY1HaF9ACnmc5VY62aoxo"
        }
      ],
      "services": {
        "appinvite_service": {
          "other_platform_oauth_client": [
            {
              "client_id": "322516920929-on448i6sc9cb6rn3bj4cfgab37kpg9vo.apps.googleusercontent.com",
              "client_type": 3
            }
          ]
        }
      }
    }
  ],
  "configuration_version": "1"
}